LegadoParser2/BookInfo.py
LegadoParser2/Chapter.py
LegadoParser2/ChapterList.py
LegadoParser2/Debug.py
LegadoParser2/FormatUtils.py
LegadoParser2/GSON.py
LegadoParser2/HttpRequset2.py
LegadoParser2/RuleCompile.py
LegadoParser2/RuleEval.py
LegadoParser2/RuleObjectEncoder.py
LegadoParser2/RuleType.py
LegadoParser2/Search.py
LegadoParser2/StrOperate.py
LegadoParser2/Tokenize2.py
LegadoParser2/__init__.py
LegadoParser2/config.py
LegadoParser2/entities.py
LegadoParser2/exceptions.py
LegadoParser2/fontutils.py
LegadoParser2/test.py
LegadoParser2/utils.py
LegadoParser2/webview.py
LegadoParser2/RuleDefault/EndRule.py
LegadoParser2/RuleDefault/RuleDefaultEfficient2.py
LegadoParser2/RuleDefault/__init__.py
LegadoParser2/RuleJs/JS.py
LegadoParser2/RuleJs/__init__.py
LegadoParser2/RuleJs/jsExtension.js
LegadoParser2/RuleJs/jsExtension.py
LegadoParser2/RuleJsonPath/RuleJsonPath.py
LegadoParser2/RuleJsonPath/__init__.py
LegadoParser2/RuleRegex/RuleRegex.py
LegadoParser2/RuleRegex/__init__.py
LegadoParser2/RuleUrl/BodyType.py
LegadoParser2/RuleUrl/Url.py
LegadoParser2/RuleUrl/UrlEval.py
LegadoParser2/RuleUrl/__init__.py
LegadoParser2/RuleXpath/RuleXpath.py
LegadoParser2/RuleXpath/__init__.py
LegadoParser2/html5_parser/__init__.py
LegadoParser2/html5_parser/dom.py
LegadoParser2/html5_parser/encoding_names.py
LegadoParser2/html5_parser/encoding_parser.py
LegadoParser2/html5_parser/libexslt.dll
LegadoParser2/html5_parser/libxml2.dll
LegadoParser2/html5_parser/libxslt.dll
LegadoParser2/html5_parser/soup.py
LegadoParser2/html5_parser/stdlib_etree.py
LegadoParser2/html5_parser/zlib1.dll
LegadoParser2/quickjs/__init__.py
LegadoParser2-0.0.3.dist-info/LICENSE
LegadoParser2-0.0.3.dist-info/METADATA
LegadoParser2-0.0.3.dist-info/WHEEL
LegadoParser2-0.0.3.dist-info/top_level.txt
LegadoParser2-0.0.3.dist-info/RECORD
