Metadata-Version: 2.1
Name: LegadoParser2
Version: 0.0.3
Summary: parse legado rule package
Home-page: https://github.com/pypa/sampleproject
Author: Legado
Author-email: 843019417@qq.com
Project-URL: Bug Tracker, https://github.com/pypa/sampleproject/issues
Classifier: Programming Language :: Python :: 3
Classifier: License :: OSI Approved :: MIT License
Classifier: Operating System :: OS Independent
Requires-Python: >=3.6
License-File: LICENSE
